zope.browserpage-5.0-py3.9-nspkg.pth
zope/browserpage/__init__.py
zope/browserpage/configure.zcml
zope/browserpage/meta.zcml
zope/browserpage/metaconfigure.py
zope/browserpage/metadirectives.py
zope/browserpage/namedtemplate.py
zope/browserpage/namedtemplate.rst
zope/browserpage/simpleviewclass.py
zope/browserpage/viewpagetemplatefile.py
zope/browserpage/tests/__init__.py
zope/browserpage/tests/namedtemplate.pt
zope/browserpage/tests/sample.py
zope/browserpage/tests/simpletestview.py
zope/browserpage/tests/test.pt
zope/browserpage/tests/test_boundpagetemplate.py
zope/browserpage/tests/test_expressiontype.py
zope/browserpage/tests/test_metaconfigure.py
zope/browserpage/tests/test_namedtemplate.py
zope/browserpage/tests/test_page.py
zope/browserpage/tests/test_simpleviewclass.py
zope/browserpage/tests/test_viewzpt.py
zope/browserpage/tests/testsimpleviewclass.pt
zope/browserpage/tests/testxml.pt
zope/browserpage/tests/testfiles/test.pt
zope/browserpage/tests/testfiles/test2.pt
zope/browserpage/tests/testfiles/test3.pt
zope.browserpage-5.0.dist-info/LICENSE.txt
zope.browserpage-5.0.dist-info/METADATA
zope.browserpage-5.0.dist-info/WHEEL
zope.browserpage-5.0.dist-info/namespace_packages.txt
zope.browserpage-5.0.dist-info/top_level.txt
zope.browserpage-5.0.dist-info/RECORD
